sneks/__init__.py
sneks/bash.py
sneks/config.py
sneks/ddb.py
sneks/git.py
sneks/gps.py
sneks/snekjson.py
sneks/ddb/__init__.py
sneks/ddb/orm.py
sneks/ddb/toco.py
sneks/sam/__init__.py
sneks/sam/api.py
sneks/sam/decorators.py
sneks/sam/events.py
sneks/sam/exceptions.py
sneks/sam/preprocessors.py
sneks/sam/request_core.py
sneks/sam/response_core.py
sneks/sam/stack_info.py
sneks/sam/ui_stuff.py
sneks-0.0.30.data/scripts/bashify_sneks_conf
sneks-0.0.30.data/scripts/bundle_lambda
sneks-0.0.30.data/scripts/get_sam_args
sneks-0.0.30.data/scripts/install_dependencies
sneks-0.0.30.data/scripts/publish_sam_stack
sneks-0.0.30.data/scripts/setup_build_dir
sneks-0.0.30.data/scripts/sneks
sneks-0.0.30.data/scripts/sneks_bashify-sneks-conf
sneks-0.0.30.data/scripts/sneks_bundle-lambda
sneks-0.0.30.data/scripts/sneks_get-sam-args
sneks-0.0.30.data/scripts/sneks_get-sam-logs
sneks-0.0.30.data/scripts/sneks_install-dependencies
sneks-0.0.30.data/scripts/sneks_publish-sam-stack
sneks-0.0.30.data/scripts/sneks_setup-build-dir
sneks-0.0.30.data/scripts/sneks_upload-static-assets
sneks-0.0.30.data/scripts/upload_static_assets
sneks-0.0.30.dist-info/LICENSE
sneks-0.0.30.dist-info/METADATA
sneks-0.0.30.dist-info/WHEEL
sneks-0.0.30.dist-info/top_level.txt
sneks-0.0.30.dist-info/RECORD
