Metadata-Version: 2.1
Name: sneks
Version: 0.0.30
Summary: Basic python utilities.
Home-page: https://github.com/stevenorum/sneks
Author: Steve Norum
Author-email: sn@drunkenrobotlabs.org
License: UNKNOWN
Download-URL: https://github.com/stevenorum/sneks/archive/0.0.30.tar.gz
Keywords: python
Platform: UNKNOWN
Requires-Dist: beautifulsoup4
Requires-Dist: boto3
Requires-Dist: jinja2
